qlbm/__init__.py
qlbm/components/__init__.py
qlbm/components/base.py
qlbm/components/collisionless/__init__.py
qlbm/components/collisionless/bounceback_reflection.py
qlbm/components/collisionless/cqlbm.py
qlbm/components/collisionless/primitives.py
qlbm/components/collisionless/specular_reflection.py
qlbm/components/collisionless/streaming.py
qlbm/components/common/__init__.py
qlbm/components/common/primitives.py
qlbm/components/common/cbse_collision/__init__.py
qlbm/components/common/cbse_collision/cbse_collision.py
qlbm/components/common/cbse_collision/cbse_permutation.py
qlbm/components/common/cbse_collision/cbse_redistribution.py
qlbm/components/lqlga/__init__.py
qlbm/components/lqlga/collision.py
qlbm/components/lqlga/initial.py
qlbm/components/lqlga/lqlga.py
qlbm/components/lqlga/measurement.py
qlbm/components/lqlga/reflection.py
qlbm/components/lqlga/streaming.py
qlbm/components/spacetime/__init__.py
qlbm/components/spacetime/measurement.py
qlbm/components/spacetime/spacetime.py
qlbm/components/spacetime/streaming.py
qlbm/components/spacetime/collision/__init__.py
qlbm/components/spacetime/collision/d2q4_old.py
qlbm/components/spacetime/collision/eqc_collision.py
qlbm/components/spacetime/initial/__init__.py
qlbm/components/spacetime/initial/pointwise.py
qlbm/components/spacetime/initial/volumetric.py
qlbm/components/spacetime/reflection/__init__.py
qlbm/components/spacetime/reflection/pointwise.py
qlbm/components/spacetime/reflection/volumetric.py
qlbm/infra/__init__.py
qlbm/infra/compiler.py
qlbm/infra/reinitialize/__init__.py
qlbm/infra/reinitialize/base.py
qlbm/infra/reinitialize/identity_reinitializer.py
qlbm/infra/reinitialize/spacetime_reinitializer.py
qlbm/infra/result/__init__.py
qlbm/infra/result/base.py
qlbm/infra/result/collisionless_result.py
qlbm/infra/result/lqlga_result.py
qlbm/infra/result/spacetime_result.py
qlbm/infra/runner/__init__.py
qlbm/infra/runner/base.py
qlbm/infra/runner/mpi_qulacs.py
qlbm/infra/runner/qiskit_runner.py
qlbm-0.0.6.dist-info/licenses/LICENSE
qlbm-0.0.6.dist-info/METADATA
qlbm-0.0.6.dist-info/WHEEL
qlbm-0.0.6.dist-info/top_level.txt
qlbm-0.0.6.dist-info/RECORD
