Metadata-Version: 2.4
Name: qlbm
Version: 0.0.6
Summary: Quantum Algorithms for Lattice Boltzmann Methods.
Author: qlbm authors
Author-email: qcfd-EWI@tudelft.nl
Maintainer-email: Calin Georgescu <c.a.georgescu@tudelft.nl>
License: MPL-2.0
Project-URL: Homepage, https://qcfd-lab.github.io/qlbm/
Classifier: Environment :: Console
Classifier: Development Status :: 4 - Beta
Classifier: Intended Audience :: Science/Research
Classifier: License :: OSI Approved :: Mozilla Public License 2.0 (MPL 2.0)
Classifier: Operating System :: MacOS
Classifier: Operating System :: Microsoft :: Windows
Classifier: Operating System :: POSIX :: Linux
Classifier: Programming Language :: Python :: 3 :: Only
Classifier: Programming Language :: Python :: 3.12
Classifier: Programming Language :: Python :: 3.13
Classifier: Topic :: Scientific/Engineering :: Quantum Computing
Requires-Python: >=3.12
License-File: LICENSE
Requires-Dist: numpy>=2.2
Requires-Dist: numpy-stl>=3.1
Requires-Dist: pandas>=2.2.2
Requires-Dist: pylatexenc>=2.10
Requires-Dist: pytket>=1.29.2
Requires-Dist: pytket-qiskit
Requires-Dist: pytket-qulacs>=0.33
Requires-Dist: qiskit>=2.0
Requires-Dist: qiskit_qasm3_import>=0.4.2
Requires-Dist: qiskit-qulacs>=0.1.0
Requires-Dist: tqdm>=4.66
Requires-Dist: vtk
Provides-Extra: dev
Requires-Dist: mypy==1.16.1; extra == "dev"
Requires-Dist: pytest; extra == "dev"
Requires-Dist: pytest-cov; extra == "dev"
Requires-Dist: coverage; extra == "dev"
Requires-Dist: ruff>=0.9.2; extra == "dev"
Requires-Dist: matplotlib; extra == "dev"
Requires-Dist: seaborn; extra == "dev"
Requires-Dist: ipykernel; extra == "dev"
Requires-Dist: sphinx==8.0.2; extra == "dev"
Requires-Dist: pydata-sphinx-theme; extra == "dev"
Requires-Dist: pyvista[jupyter]; extra == "dev"
Requires-Dist: imageio; extra == "dev"
Provides-Extra: cpu
Requires-Dist: qulacs>=0.6.3; extra == "cpu"
Requires-Dist: qiskit-aer>=0.16; extra == "cpu"
Provides-Extra: gpu
Requires-Dist: qulacs-gpu>=0.3; extra == "gpu"
Requires-Dist: qiskit-aer-gpu>=0.13; extra == "gpu"
Provides-Extra: mpiqulacs
Requires-Dist: mpi4py>=3.1; extra == "mpiqulacs"
Requires-Dist: mpiQulacs>=1.3.1; extra == "mpiqulacs"
Requires-Dist: qiskit-aer>=0.13; extra == "mpiqulacs"
Provides-Extra: docs
Requires-Dist: sphinx; extra == "docs"
Requires-Dist: pydata-sphinx-theme; extra == "docs"
Requires-Dist: sphinxcontrib-bibtex; extra == "docs"
Requires-Dist: sphinx_autodoc_typehints; extra == "docs"
Requires-Dist: sphinx_copybutton; extra == "docs"
Requires-Dist: sphinx_design; extra == "docs"
Requires-Dist: nbsphinx; extra == "docs"
Requires-Dist: nbsphinx-link; extra == "docs"
Dynamic: license-file
